{
  "title": {
    "en": "At the Restaurant",
    "uk": "У ресторані"
  },
  "audio": "content/audio/restaurant_extended.mp3",
  "sentences": [
    {
      "french": "Bonsoir, vous avez réservé?",
      "translation": {
        "en": "Good evening, do you have a reservation?",
        "uk": "Добрий вечір, ви маєте резервацію?"
      },
      "start": 0,
      "end": 2,
      "voice_type": "male"
    },
    {
      "french": "Oui, j'ai réservé pour deux personnes au nom de Martin.",
      "translation": {
        "en": "Yes, I have a reservation for two people under the name Martin.",
        "uk": "Так, я зарезервував столик на двох на ім'я Мартін."
      },
      "start": 2,
      "end": 7,
      "voice_type": "male2"
    },
    {
      "french": "Parfait, suivez-moi s'il vous plaît.",
      "translation": {
        "en": "Perfect, please follow me.",
        "uk": "Чудово, прошу за мною."
      },
      "start": 7,
      "end": 10,
      "voice_type": "male"
    },
    {
      "french": "Voici la carte. Je vous laisse choisir.",
      "translation": {
        "en": "Here's the menu. I'll give you time to choose.",
        "uk": "Ось меню. Я дам вам час вибрати."
      },
      "start": 10,
      "end": 15,
      "voice_type": "male"
    },
    {
      "french": "Qu'est-ce que vous recommandez?",
      "translation": {
        "en": "What do you recommend?",
        "uk": "Що ви рекомендуєте?"
      },
      "start": 15,
      "end": 18,
      "voice_type": "male2"
    },
    {
      "french": "Le plat du jour est un steak avec des légumes grillés.",
      "translation": {
        "en": "Today's special is steak with grilled vegetables.",
        "uk": "Стравою дня є стейк з гриль-овочами."
      },
      "start": 18,
      "end": 21,
      "voice_type": "male"
    },
    {
      "french": "Très bien, je vais prendre ça.",
      "translation": {
        "en": "Very well, I'll have that.",
        "uk": "Дуже добре, я візьму це."
      },
      "start": 21,
      "end": 24,
      "voice_type": "male2"
    },
    {
      "french": "Et pour vous, madame?",
      "translation": {
        "en": "And for you, madam?",
        "uk": "А для вас, мадам?"
      },
      "start": 24,
      "end": 26,
      "voice_type": "male"
    },
    {
      "french": "Je prendrai une salade niçoise, s'il vous plaît.",
      "translation": {
        "en": "I'll have a Niçoise salad, please.",
        "uk": "Я візьму салат Нісуаз, будь ласка."
      },
      "start": 27,
      "end": 30,
      "voice_type": "female"
    },
    {
      "french": "Et comme boisson?",
      "translation": {
        "en": "And for drinks?",
        "uk": "А що будете пити?"
      },
      "start": 30,
      "end": 33,
      "voice_type": "male"
    },
    {
      "french": "Une bouteille d'eau minérale et un verre de vin rouge.",
      "translation": {
        "en": "A bottle of mineral water and a glass of red wine.",
        "uk": "Пляшку мінеральної води та келих червоного вина."
      },
      "start": 33,
      "end": 37,
      "voice_type": "male2"
    },
    {
      "french": "Très bien. Vous voulez du pain avec votre repas?",
      "translation": {
        "en": "Very well. Would you like some bread with your meal?",
        "uk": "Дуже добре. Бажаєте хліб до вашої страви?"
      },
      "start": 37,
      "end": 41,
      "voice_type": "male"
    },
    {
      "french": "Oui, merci.",
      "translation": {
        "en": "Yes, thank you.",
        "uk": "Так, дякую."
      },
      "start": 41,
      "end": 43,
      "voice_type": "male2"
    },
    {
      "french": "Voici votre repas. Bon appétit!",
      "translation": {
        "en": "Here is your meal. Enjoy your meal!",
        "uk": "Ось ваша страва. Смачного!"
      },
      "start": 43,
      "end": 48,
      "voice_type": "male"
    },
    {
      "french": "Merci beaucoup!",
      "translation": {
        "en": "Thank you very much!",
        "uk": "Дякую дуже!"
      },
      "start": 48,
      "end": 50,
      "voice_type": "female"
    },
    {
      "french": "Tout se passe bien?",
      "translation": {
        "en": "Is everything going well?",
        "uk": "Все добре?"
      },
      "start": 50,
      "end": 52,
      "voice_type": "male"
    },
    {
      "french": "Oui, c'est délicieux!",
      "translation": {
        "en": "Yes, it's delicious!",
        "uk": "Так, це дуже смачно!"
      },
      "start": 52,
      "end": 54,
      "voice_type": "male2"
    },
    {
      "french": "Souhaitez-vous un dessert?",
      "translation": {
        "en": "Would you like a dessert?",
        "uk": "Бажаєте десерт?"
      },
      "start": 54,
      "end": 58,
      "voice_type": "male"
    },
    {
      "french": "Oui, une tarte aux pommes pour moi, s'il vous plaît.",
      "translation": {
        "en": "Yes, an apple tart for me, please.",
        "uk": "Так, яблучний пиріг для мене, будь ласка."
      },
      "start": 58,
      "end": 61,
      "voice_type": "male2"
    },
    {
      "french": "Et pour vous, madame?",
      "translation": {
        "en": "And for you, madam?",
        "uk": "А для вас, мадам?"
      },
      "start": 61,
      "end": 63,
      "voice_type": "male"
    },
    {
      "french": "Un café et une crème brûlée, s'il vous plaît.",
      "translation": {
        "en": "A coffee and a crème brûlée, please.",
        "uk": "Каву та крем-брюле, будь ласка."
      },
      "start": 63,
      "end": 67,
      "voice_type": "female"
    },
    {
      "french": "D'accord. Je vous apporte ça tout de suite.",
      "translation": {
        "en": "Alright. I'll bring that right away.",
        "uk": "Гаразд. Я зараз принесу."
      },
      "start": 67,
      "end": 72,
      "voice_type": "male"
    },
    {
      "french": "L'addition, s'il vous plaît.",
      "translation": {
        "en": "The check, please.",
        "uk": "Рахунок, будь ласка."
      },
      "start": 72,
      "end": 75,
      "voice_type": "male2"
    },
    {
      "french": "Voici votre addition. Cela fait 42 euros.",
      "translation": {
        "en": "Here is your bill. That will be 42 euros.",
        "uk": "Ось ваш рахунок. З вас 42 євро."
      },
      "start": 75,
      "end": 79,
      "voice_type": "male"
    },
    {
      "french": "Je paie par carte.",
      "translation": {
        "en": "I'll pay by card.",
        "uk": "Я оплачую карткою."
      },
      "start": 79,
      "end": 81,
      "voice_type": "male2"
    },
    {
      "french": "Merci beaucoup et bonne soirée!",
      "translation": {
        "en": "Thank you very much and have a nice evening!",
        "uk": "Дуже дякую і гарного вечора!"
      },
      "start": 81,
      "end": 85,
      "voice_type": "male"
    }
  ]
}